Workbook

Sheet 0_TongHop
A1: TỔNG HỢP — pass-rate + Điểm TB (người chấm) · auto-metrics (máy)
A3: Version | B3: Số câu | C3: Đã chấm | D3: Số Đạt | E3: Pass-rate % | F3: Điểm TB /5 | G3: Auto: tình huống % | H3: Auto: cấu trúc % | I3: Auto: không trùng % | J3: JSON %
A4: v1_baseline | B4: 120 | C4: =COUNT(v1_baseline!J2:J121) -> 0 | D4: =COUNTIF(v1_baseline!K2:K121,"Đạt") -> 0 | E4: =IF(C4=0,"",ROUND(D4/C4*100,1)) | F4: =IFERROR(ROUND(AVERAGE(v1_baseline!J2:J121),2),"") | G4: 11.7 | H4: 100.0 | I4: 97.5 | J4: 100.0
A5: v2_skill_extraction | B5: 111 | C5: =COUNT(v2_skill_extraction!J2:J112) -> 0 | D5: =COUNTIF(v2_skill_extraction!K2:K112,"Đạt") -> 0 | E5: =IF(C5=0,"",ROUND(D5/C5*100,1)) | F5: =IFERROR(ROUND(AVERAGE(v2_skill_extraction!J2:J112),2),"") | G5: 27.9 | H5: 99.1 | I5: 100.0 | J5: 100.0
A6: v3_fewshot | B6: 111 | C6: =COUNT(v3_fewshot!J2:J112) -> 0 | D6: =COUNTIF(v3_fewshot!K2:K112,"Đạt") -> 0 | E6: =IF(C6=0,"",ROUND(D6/C6*100,1)) | F6: =IFERROR(ROUND(AVERAGE(v3_fewshot!J2:J112),2),"") | G6: 43.2 | H6: 99.1 | I6: 100.0 | J6: 100.0
A7: v4_situational | B7: 119 | C7: =COUNT(v4_situational!J2:J120) -> 0 | D7: =COUNTIF(v4_situational!K2:K120,"Đạt") -> 0 | E7: =IF(C7=0,"",ROUND(D7/C7*100,1)) | F7: =IFERROR(ROUND(AVERAGE(v4_situational!J2:J120),2),"") | G7: 50.4 | H7: 99.2 | I7: 97.5 | J7: 100.0
A8: v5_self_critique | B8: 111 | C8: =COUNT(v5_self_critique!J2:J112) -> 0 | D8: =COUNTIF(v5_self_critique!K2:K112,"Đạt") -> 0 | E8: =IF(C8=0,"",ROUND(D8/C8*100,1)) | F8: =IFERROR(ROUND(AVERAGE(v5_self_critique!J2:J112),2),"") | G8: 60.4 | H8: 100.0 | I8: 100.0 | J8: 100.0
A11: GHI CHÚ:
A12: • Pass-rate, Số Đạt, Đã chấm, Điểm TB /5: TỰ TÍNH khi bạn gõ điểm vào sheet version.
A13: • Mỗi câu: gõ 0–5 vào 5 cột Correctness/Relevance/Distractor/Tình huống/Rõ ràng (ô VÀNG).
A14: -> Điểm TB từng câu tự ra; Đạt = 'Đạt' nếu Điểm TB ≥ 4.
A15: • CHẤM ĐỦ cả 5 version (mọi dòng vàng) — so sánh công bằng trên cùng 12 JD.
A16: • Cột 'Auto: ...' do code metrics.py tính, KHÔNG phải người chấm (tham khảo; cấu trúc/JSON kịch trần nên không phân biệt version).
A17: • Trục QUYẾT ĐỊNH cho luận văn = Pass-rate người chấm, đối chiếu xu hướng auto tình huống %.
A18: • cskh_junior ở v4/v5 có 2 câu nhãn skill lỗi (model qwen2.5 tuôn tiếng Trung) — nội dung câu vẫn tiếng Việt, cứ chấm bình thường.

Sheet v1_baseline
A1: STT | B1: JD_id | C1: Skill | D1: Câu hỏi (đầy đủ) | E1: Correctness | F1: Relevance | G1: Distractor | H1: Tình huống | I1: Rõ ràng | J1: Điểm TB | K1: Đạt | L1: Ghi chú
A2: 1 | B2: dev_dotnet_junior | C2: (1 phát – không tách skill) | D2: Ngôn ngữ lập trình chính được sử dụng trong vị trí này là gì? A. Python B. Java C. C# ✓ D. JavaScript | J2: =IF(COUNT(E2:I2)=5,AVERAGE(E2:I2),"") | K2: =IF(J2="","",IF(J2>=4,"Đạt","Không"))
A3: 2 | B3: dev_dotnet_junior | C3: (1 phát – không tách skill) | D3: Một yêu cầu kỹ thuật quan trọng để ứng tuyển vào vị trí này là gì? A. Nắm vững SQL Server B. Hiểu về HTTP/REST ✓ C. Có kinh nghiệm với Vue.js D. Biết Node.js | J3: =IF(COUNT(E3:I3)=5,AVERAGE(E3:I3),"") | K3: =IF(J3="","",IF(J3>=4,"Đạt","Không"))
A4: 3 | B4: dev_dotnet_junior | C4: (1 phát – không tách skill) | D4: Ứng viên cần nắm vững kiến thức nào trong C# để ứng tuyển? A. LINQ ✓ B. HTML C. CSS D. JavaScript | J4: =IF(COUNT(E4:I4)=5,AVERAGE(E4:I4),"") | K4: =IF(J4="","",IF(J4>=4,"Đạt","Không"))
A5: 4 | B5: dev_dotnet_junior | C5: (1 phát – không tách skill) | D5: Đối với vị trí này, ứng viên đã làm gì sẽ được ưu tiên? A. Thực tập tại công ty khác B. Làm đồ án hoặc thực tập có sản phẩm thực tế ✓ C. Học lập trình tự do D. Xây dựng website cá nhân | J5: =IF(COUNT(E5:I5)=5,AVERAGE(E5:I5),"") | K5: =IF(J5="","",IF(J5>=4,"Đạt","Không"))
A6: 5 | B6: dev_dotnet_junior | C6: (1 phát – không tách skill) | D6: Ứng viên cần viết unit test cho các hàm được giao, công cụ nào thường được sử dụng trong vị trí này? A. Selenium B. NUnit ✓ C. React D. Angular | J6: =IF(COUNT(E6:I6)=5,AVERAGE(E6:I6),"") | K6: =IF(J6="","",IF(J6>=4,"Đạt","Không"))
A7: 6 | B7: dev_dotnet_junior | C7: (1 phát – không tách skill) | D7: Một ứng viên có thể viết API RESTful cơ bản cho vị trí này, HTTP/REST là gì? A. Một loại ngôn ngữ lập trình B. Phương thức truyền dữ liệu qua mạng internet C. Mô hình thiết kế web ✓ D. Công cụ quản lý dự án | J7: =IF(COUNT(E7:I7)=5,AVERAGE(E7:I7),"") | K7: =IF(J7="","",IF(J7>=4,"Đạt","Không"))
A8: 7 | B8: dev_dotnet_junior | C8: (1 phát – không tách skill) | D8: Ứng viên cần sử dụng công cụ nào để quản lý mã nguồn? A. Git ✓ B. SVN C. TFS D. Bitbucket | J8: =IF(COUNT(E8:I8)=5,AVERAGE(E8:I8),"") | K8: =IF(J8="","",IF(J8>=4,"Đạt","Không"))
A9: 8 | B9: dev_dotnet_junior | C9: (1 phát – không tách skill) | D9: Một yêu cầu kỹ thuật quan trọng khác đối với vị trí này là gì? A. Nắm vững JavaScript B. Hiểu về Entity Framework Core ✓ C. Có kinh nghiệm với Angular D. Biết Node.js | J9: =IF(COUNT(E9:I9)=5,AVERAGE(E9:I9),"") | K9: =IF(J9="","",IF(J9>=4,"Đạt","Không"))
A10: 9 | B10: dev_dotnet_junior | C10: (1 phát – không tách skill) | D10: Ứng viên cần viết API RESTful cơ bản, trong đó HTTP/REST là gì? A. Một loại ngôn ngữ lập trình B. Phương thức truyền dữ liệu qua mạng internet ✓ C. Mô hình thiết kế web D. Công cụ quản lý dự án | J10: =IF(COUNT(E10:I10)=5,AVERAGE(E10:I10),"") | K10: =IF(J10="","",IF(J10>=4,"Đạt","Không"))
A11: 10 | B11: dev_dotnet_junior | C11: (1 phát – không tách skill) | D11: Ứng viên cần viết unit test cho các hàm được giao, công cụ nào thường được sử dụng trong vị trí này? A. Selenium B. NUnit ✓ C. React D. Angular | J11: =IF(COUNT(E11:I11)=5,AVERAGE(E11:I11),"") | K11: =IF(J11="","",IF(J11>=4,"Đạt","Không"))
A12: 11 | B12: dev_dotnet_senior | C12: (1 phát – không tách skill) | D12: Ứng viên cần có bao nhiêu năm kinh nghiệm với C#/.NET để đáp ứng yêu cầu của vị trí? A. 1 năm B. 2 năm C. 4+ năm D. 6 năm ✓ | J12: =IF(COUNT(E12:I12)=5,AVERAGE(E12:I12),"") | K12: =IF(J12="","",IF(J12>=4,"Đạt","Không"))
A13: 12 | B13: dev_dotnet_senior | C13: (1 phát – không tách skill) | D13: Trong Entity Framework Core, phương pháp nào được sử dụng để tối ưu truy vấn và tránh N+1 query? A. Include() ✓ B. AsNoTracking() C. Load() D. ThenInclude() | J13: =IF(COUNT(E13:I13)=5,AVERAGE(E13:I13),"") | K13: =IF(J13="","",IF(J13>=4,"Đạt","Không"))
... A121: 120 | B121: edge_jd_thieu_kythuat | C121: (1 phát – không tách skill) | D121: Ứng viên cần có kỹ năng gì để hỗ trợ các phòng ban khi cần? A. Kỹ năng lái xe B. Kỹ năng giao tiếp C. Kỹ năng sử dụng máy tính văn phòng ✓ D. Kỹ năng bán hàng | J121: =IF(COUNT(E121:I121)=5,AVERAGE(E121:I121),"") | K121: =IF(J121="","",IF(J121>=4,"Đạt","Không"))

Sheet v2_skill_extraction
A1: STT | B1: JD_id | C1: Skill | D1: Câu hỏi (đầy đủ) | E1: Correctness | F1: Relevance | G1: Distractor | H1: Tình huống | I1: Rõ ràng | J1: Điểm TB | K1: Đạt | L1: Ghi chú
A2: 1 | B2: dev_dotnet_junior | C2: C# OOP | D2: Trong C#, lớp nào sau đây là lớp gốc nhất và từ đó tất cả các lớp khác kế thừa? A. System.Object ✓ B. System.Class C. BaseClass D. RootClass | J2: =IF(COUNT(E2:I2)=5,AVERAGE(E2:I2),"") | K2: =IF(J2="","",IF(J2>=4,"Đạt","Không"))
A3: 2 | B3: dev_dotnet_junior | C3: C# OOP | D3: Trong lập trình hướng đối tượng, phương thức nào sau đây được sử dụng để khởi tạo trạng thái ban đầu của một đối tượng? A. Initialize B. Constructor ✓ C. Setup D. Start | J3: =IF(COUNT(E3:I3)=5,AVERAGE(E3:I3),"") | K3: =IF(J3="","",IF(J3>=4,"Đạt","Không"))
A4: 3 | B4: dev_dotnet_junior | C4: LINQ | D4: Trong LINQ, phương thức nào sau đây được sử dụng để lọc các phần tử trong một sequence dựa trên điều kiện? A. Where ✓ B. Select C. OrderBy D. GroupBy | J4: =IF(COUNT(E4:I4)=5,AVERAGE(E4:I4),"") | K4: =IF(J4="","",IF(J4>=4,"Đạt","Không"))
A5: 4 | B5: dev_dotnet_junior | C5: HTTP/REST | D5: Trong HTTP/REST, phương thức nào được sử dụng để tạo một tài nguyên mới? A. GET B. POST ✓ C. PUT D. DELETE | J5: =IF(COUNT(E5:I5)=5,AVERAGE(E5:I5),"") | K5: =IF(J5="","",IF(J5>=4,"Đạt","Không"))
A6: 5 | B6: dev_dotnet_junior | C6: SQL SELECT, JOIN | D6: Trong SQL, để lấy tất cả các cột từ bảng 'Customers' và 'Orders', bạn sẽ sử dụng câu lệnh nào? A. 'SELECT * FROM Customers JOIN Orders' B. 'SELECT * FROM Customers INNER JOIN Orders' ✓ C. 'SELECT * FROM Customers AND Orders' D. 'SELECT * FROM Customers LEFT JOIN Orders' | J6: =IF(COUNT(E6:I6)=5,AVERAGE(E6:I6),"") | K6: =IF(J6="","",IF(J6>=4,"Đạt","Không"))
A7: 6 | B7: dev_dotnet_junior | C7: SQL SELECT, JOIN | D7: Nếu bạn muốn lấy tất cả các khách hàng từ bảng 'Customers' và chỉ những đơn đặt hàng có cùng ID khách hàng, câu lệnh SQL nào sẽ phù hợp? A. 'SELECT * FROM Customers JOIN Orders' B. 'SELECT * FROM Customers INNER JOIN Orders ON Customers.CustomerID = Orders.CustomerID' ✓ C. 'SELECT * FROM Customers LEFT JOIN Orders' D. 'SELECT * FROM Customers RIGHT JOIN Orders' | J7: =IF(COUNT(E7:I7)=5,AVERAGE(E7:I7),"") | K7: =IF(J7="","",IF(J7>=4,"Đạt","Không"))
A8: 7 | B8: dev_dotnet_junior | C8: Entity Framework Core | D8: Trong Entity Framework Core, phương thức nào sau đây được sử dụng để thực hiện lệnh INSERT vào cơ sở dữ liệu? A. SaveChanges() ✓ B. Add() C. Insert() D. Create() | J8: =IF(COUNT(E8:I8)=5,AVERAGE(E8:I8),"") | K8: =IF(J8="","",IF(J8>=4,"Đạt","Không"))
A9: 8 | B9: dev_dotnet_junior | C9: API RESTful | D9: API RESTful tuân theo nguyên tắc nào sau đây? A. API phải hỗ trợ cả GET, POST, PUT và DELETE B. API chỉ nên sử dụng HTTP status code 200 OK C. API không cần tuân theo bất kỳ nguyên tắc nào D. API phải tuân thủ các nguyên tắc của kiến trúc REST như stateless, cacheable, client-server ✓ | J9: =IF(COUNT(E9:I9)=5,AVERAGE(E9:I9),"") | K9: =IF(J9="","",IF(J9>=4,"Đạt","Không"))
A10: 9 | B10: dev_dotnet_junior | C10: Git | D10: Trong Git, lệnh nào sau đây được sử dụng để ghi nhận các thay đổi trong repository? A. git commit ✓ B. git push C. git pull D. git clone | J10: =IF(COUNT(E10:I10)=5,AVERAGE(E10:I10),"") | K10: =IF(J10="","",IF(J10>=4,"Đạt","Không"))
A11: 10 | B11: dev_dotnet_junior | C11: Unit Testing | D11: Trong Unit Testing, phương pháp nào sau đây không phải là một trong những công cụ phổ biến để thực hiện các bài kiểm thử đơn vị cho mã .NET? A. NUnit B. MSTest C. Junit ✓ D. xUnit | J11: =IF(COUNT(E11:I11)=5,AVERAGE(E11:I11),"") | K11: =IF(J11="","",IF(J11>=4,"Đạt","Không"))
A12: 11 | B12: dev_dotnet_senior | C12: Thiết kế kiến trúc microservices | D12: Trong kiến trúc microservices, component nào dưới đây thường đóng vai trò là trung tâm điều phối giữa các dịch vụ nhỏ? A. Database B. API Gateway ✓ C. Load Balancer D. Service Discovery | J12: =IF(COUNT(E12:I12)=5,AVERAGE(E12:I12),"") | K12: =IF(J12="","",IF(J12>=4,"Đạt","Không"))
A13: 12 | B13: dev_dotnet_senior | C13: Thiết kế kiến trúc microservices | D13: Khi thiết kế microservices, nguyên tắc nào dưới đây không phù hợp để đảm bảo tính linh hoạt và khả năng mở rộng? A. Mỗi dịch vụ chỉ xử lý một chức năng cụ thể B. Sử dụng cùng một cơ sở dữ liệu cho tất cả các dịch vụ ✓ C. Tối ưu hóa việc tái sử dụng mã giữa các dịch vụ D. Cung cấp giao diện API rõ ràng và độc lập | J13: =IF(COUNT(E13:I13)=5,AVERAGE(E13:I13),"") | K13: =IF(J13="","",IF(J13>=4,"Đạt","Không"))
... A112: 111 | B112: edge_jd_thieu_kythuat | C112: Quản lý lịch hẹn và lịch trình | D112: Trong trường hợp một nhân viên có lịch trình bận rộn và nhiều cuộc hẹn, chuyên viên Văn phòng nên sử dụng công cụ nào để tối ưu hóa quản lý thời gian? A. Một cuốn sổ tay giấy B. Một ứng dụng quản lý lịch hẹn di động ✓ C. Một bảng lịch giấy D. Email cá nhân | J112: =IF(COUNT(E112:I112)=5,AVERAGE(E112:I112),"") | K112: =IF(J112="","",IF(J112>=4,"Đạt","Không"))

Sheet v3_fewshot
A1: STT | B1: JD_id | C1: Skill | D1: Câu hỏi (đầy đủ) | E1: Correctness | F1: Relevance | G1: Distractor | H1: Tình huống | I1: Rõ ràng | J1: Điểm TB | K1: Đạt | L1: Ghi chú
A2: 1 | B2: dev_dotnet_junior | C2: C# OOP | D2: Trong C#, khi sử dụng lớp基线代码需要翻译成中文，以下是修改后的版本：````json { A. public class Program { public void Main() { Console.WriteLine("Hello World"); } } B. class Program { static void Main(string[] args) { Console.WriteLine("Hello World"); } } C. class Program { public void Main() { Console.WriteLine("Hello World"); } } D. public class Program { static void Main(string[] args) { Console.WriteLine("Hello World"); } } ✓ | J2: =IF(COUNT(E2:I2)=5,AVERAGE(E2:I2),"") | K2: =IF(J2="","",IF(J2>=4,"Đạt","Không"))
A3: 2 | B3: dev_dotnet_junior | C3: C# OOP | D3: Trong C#, phương thức nào sau đây không thuộc lớp Object? A. ToString() B. Equals() C. GetHashCode() D. Add() ✓ | J3: =IF(COUNT(E3:I3)=5,AVERAGE(E3:I3),"") | K3: =IF(J3="","",IF(J3>=4,"Đạt","Không"))
A4: 3 | B4: dev_dotnet_junior | C4: LINQ | D4: Để lọc ra tất cả các sản phẩm có giá bán trên 100.000 từ bảng Products sử dụng LINQ, câu lệnh nào sau đây là chính xác? A. var result = from p in Products where p.Price < 100000 select p; B. var result = from p in Products where p.Price > 100000 select p; ✓ C. var result = Products.Where(p => p.Price <= 100000); D. var result = Products.FindAll(p => p.Price >= 100000); | J4: =IF(COUNT(E4:I4)=5,AVERAGE(E4:I4),"") | K4: =IF(J4="","",IF(J4>=4,"Đạt","Không"))
A5: 4 | B5: dev_dotnet_junior | C5: HTTP/REST | D5: Trong HTTP/REST, phương thức nào được sử dụng để tạo một tài nguyên mới trên server? A. GET B. POST ✓ C. PUT D. DELETE | J5: =IF(COUNT(E5:I5)=5,AVERAGE(E5:I5),"") | K5: =IF(J5="","",IF(J5>=4,"Đạt","Không"))
A6: 5 | B6: dev_dotnet_junior | C6: SQL SELECT, JOIN | D6: Trong truy vấn SQL, nếu bạn muốn lấy tất cả các sản phẩm từ bảng Products mà chỉ hiển thị những sản phẩm có giá trên 1000, câu lệnh SELECT nào sau đây là đúng? A. SELECT * FROM Products WHERE Price < 1000 B. SELECT * FROM Products WHERE Price > 1000 ✓ C. SELECT ProductName FROM Products WHERE Price = 1000 D. SELECT * FROM Products WHERE Price >= 1000 | J6: =IF(COUNT(E6:I6)=5,AVERAGE(E6:I6),"") | K6: =IF(J6="","",IF(J6>=4,"Đạt","Không"))
A7: 6 | B7: dev_dotnet_junior | C7: SQL SELECT, JOIN | D7: Để lấy ra danh sách các sản phẩm từ bảng Products và danh sách các đơn hàng từ bảng Orders, đồng thời kết hợp (JOIN) dựa trên ID Sản phẩm, câu lệnh SQL nào sau đây là đúng? A. SELECT * FROM Products JOIN Orders ON ProductID B. SELECT * FROM Products INNER JOIN Orders ON Products.ProductID = Orders.ProductID ✓ C. SELECT * FROM Products LEFT JOIN Orders ON ProductID D. SELECT * FROM Products RIGHT JOIN Orders ON ProductID | J7: =IF(COUNT(E7:I7)=5,AVERAGE(E7:I7),"") | K7: =IF(J7="","",IF(J7>=4,"Đạt","Không"))
A8: 7 | B8: dev_dotnet_junior | C8: Entity Framework Core | D8: Trong Entity Framework Core, để thực hiện một truy vấn LINQ trả về danh sách các đối tượng Customer có tên bắt đầu với 'A', bạn sẽ sử dụng phương thức nào sau đây? A. Customer.Where(c => c.Name.StartsWith('A')).ToList() ✓ B. Customer.FindAll(c => c.Name == 'A*').ToList() C. Customer.FirstOrDefault(c => c.Name.StartsWith('A')) D. Customer.Include(c => c.Name).Where('A*').ToList() | J8: =IF(COUNT(E8:I8)=5,AVERAGE(E8:I8),"") | K8: =IF(J8="","",IF(J8>=4,"Đạt","Không"))
A9: 8 | B9: dev_dotnet_junior | C9: API RESTful | D9: API RESTful nào dưới đây không tuân theo nguyên tắc của HTTP GET method? A. GET /users B. GET /users/123 C. POST /login ✓ D. DELETE /users/123 | J9: =IF(COUNT(E9:I9)=5,AVERAGE(E9:I9),"") | K9: =IF(J9="","",IF(J9>=4,"Đạt","Không"))
A10: 9 | B10: dev_dotnet_junior | C10: Git | D10: Trong Git, lệnh nào sau đây dùng để ghi nhận các thay đổi trong code và lưu chúng vào repository? A. git commit ✓ B. git push C. git pull D. git merge | J10: =IF(COUNT(E10:I10)=5,AVERAGE(E10:I10),"") | K10: =IF(J10="","",IF(J10>=4,"Đạt","Không"))
A11: 10 | B11: dev_dotnet_junior | C11: Unit Testing | D11: Để kiểm tra tính chính xác của hàm TínhThueGiamDoc() trong lớp Thuế, bạn nên sử dụng phương pháp nào sau đây? A. Kiểm thử chấp nhận B. Kiểm thử tích hợp C. Kiểm thử đơn vị ✓ D. Kiểm thử hệ thống | J11: =IF(COUNT(E11:I11)=5,AVERAGE(E11:I11),"") | K11: =IF(J11="","",IF(J11>=4,"Đạt","Không"))
A12: 11 | B12: dev_dotnet_senior | C12: Thiết kế kiến trúc microservices | D12: Trong kiến trúc microservices, khi một dịch vụ cần truy cập dữ liệu từ một dịch vụ khác, cách tiếp cận tốt nhất là gì? A. Tạo API REST giữa hai dịch vụ ✓ B. Chia sẻ cơ sở dữ liệu trực tiếp giữa các dịch vụ C. Gửi yêu cầu qua giao thức RPC D. Bảo lưu tất cả dữ liệu vào một bảng duy nhất | J12: =IF(COUNT(E12:I12)=5,AVERAGE(E12:I12),"") | K12: =IF(J12="","",IF(J12>=4,"Đạt","Không"))
A13: 12 | B13: dev_dotnet_senior | C13: Thiết kế kiến trúc microservices | D13: Trong microservices, cách nào sau đây giúp giảm bớt sự phụ thuộc lẫn nhau giữa các dịch vụ? A. Tăng số lượng dịch vụ B. Chia nhỏ chức năng thành nhiều dịch vụ nhỏ hơn ✓ C. Sử dụng chung một cơ sở dữ liệu cho tất cả các dịch vụ D. Tạo API REST phức tạp | J13: =IF(COUNT(E13:I13)=5,AVERAGE(E13:I13),"") | K13: =IF(J13="","",IF(J13>=4,"Đạt","Không"))
... A112: 111 | B112: edge_jd_thieu_kythuat | C112: Quản lý lịch hẹn và lịch trình | D112: Trong trường hợp khách hàng không thể tham gia vào lịch hẹn đã đặt, bạn nên xử lý như thế nào? A. Hủy lịch hẹn và không thông báo lại B. Gửi email cho khách hàng về việc hủy lịch hẹn C. Tự động chuyển lịch hẹn sang người khác D. Yêu cầu khách hàng chọn lại thời gian ✓ | J112: =IF(COUNT(E112:I112)=5,AVERAGE(E112:I112),"") | K112: =IF(J112="","",IF(J112>=4,"Đạt","Không"))

Sheet v4_situational
A1: STT | B1: JD_id | C1: Skill | D1: Câu hỏi (đầy đủ) | E1: Correctness | F1: Relevance | G1: Distractor | H1: Tình huống | I1: Rõ ràng | J1: Điểm TB | K1: Đạt | L1: Ghi chú
A2: 1 | B2: dev_dotnet_junior | C2: C# OOP | D2: Bạn đang phát triển một ứng dụng quản lý thư viện. Bạn cần tạo một lớp `Sach` (Sách) để lưu thông tin sách, trong đó có các thuộc tính như `MaSach`, `TenSach`, `TacGia`. Để đảm bảo `MaSach` luôn duy nhất, bạn nên sử dụng phương thức nào sau đây? A. Tạo một phương thức `SetMaSach()` để gán giá trị cho `MaSach` B. Thêm thuộc tính `MaSach` làm thuộc tính chỉ đọc (`readonly`) và khởi tạo trong constructor ✓ C. Thêm phương thức `GetMaSach()` để trả về giá trị của `MaSach` D. Tạo một phương thức `CheckMaSachUniqueness()` để kiểm tra sự duy nhất của `MaSach` | J2: =IF(COUNT(E2:I2)=5,AVERAGE(E2:I2),"") | K2: =IF(J2="","",IF(J2>=4,"Đạt","Không"))
A3: 2 | B3: dev_dotnet_junior | C3: C# OOP | D3: Bạn đang thiết kế lớp `NhanVien` và muốn đảm bảo rằng mỗi nhân viên chỉ có một địa chỉ email duy nhất. Bạn nên sử dụng thuộc tính nào sau đây để thực hiện điều này? A. Tạo một phương thức `SetEmail()` để gán giá trị cho `Email` B. Thêm thuộc tính `Email` làm thuộc tính chỉ đọc (`readonly`) và khởi tạo trong constructor ✓ C. Thêm phương thức `GetEmail()` để trả về giá trị của `Email` D. Tạo một phương thức `CheckEmailUniqueness()` để kiểm tra sự duy nhất của `Email` | J3: =IF(COUNT(E3:I3)=5,AVERAGE(E3:I3),"") | K3: =IF(J3="","",IF(J3>=4,"Đạt","Không"))
A4: 3 | B4: dev_dotnet_junior | C4: LINQ | D4: Bạn cần lấy danh sách các sản phẩm có giá bán trên 100.000 VND từ bảng Products, nhưng chỉ muốn hiển thị tên và giá của chúng. Cách viết LINQ đúng là gì? A. var result = from p in Products where p.Price > 100000 select new { Name, Price }; B. var result = from p in Products where p.Price < 100000 select new { p.Name, p.Price }; C. var result = from p in Products where p.Price > 100000 select p; D. var result = from p in Products where p.Price > 100000 select new { p.Name, p.Price }; ✓ | J4: =IF(COUNT(E4:I4)=5,AVERAGE(E4:I4),"") | K4: =IF(J4="","",IF(J4>=4,"Đạt","Không"))
A5: 4 | B5: dev_dotnet_junior | C5: HTTP/REST | D5: Một ứng dụng RESTful API của bạn nhận được nhiều yêu cầu GET từ một client không tin cậy, dẫn đến việc sử dụng quá nhiều tài nguyên. Cách tốt nhất để giải quyết vấn đề này là gì? A. Tăng số lượng CPU trên máy chủ B. Thêm index vào đường dẫn API C. Thiết lập giới hạn rate cho các request GET ✓ D. Chuyển đổi tất cả các phương thức HTTP sang POST | J5: =IF(COUNT(E5:I5)=5,AVERAGE(E5:I5),"") | K5: =IF(J5="","",IF(J5>=4,"Đạt","Không"))
A6: 5 | B6: dev_dotnet_junior | C6: HTTP/REST | D6: Bạn nhận được yêu cầu từ một client muốn cập nhật thông tin của một sản phẩm trong hệ thống. Sản phẩm này có nhiều thuộc tính, nhưng chỉ cần cập nhật giá và tên. Cách tốt nhất để thực hiện yêu cầu này là gì? A. Sử dụng phương thức PUT với tất cả các thuộc tính B. Sử dụng phương thức POST với toàn bộ thông tin sản phẩm C. Sử dụng phương thức PATCH với chỉ những thuộc tính cần thay đổi ✓ D. Sử dụng phương thức DELETE sau đó INSERT mới | J6: =IF(COUNT(E6:I6)=5,AVERAGE(E6:I6),"") | K6: =IF(J6="","",IF(J6>=4,"Đạt","Không"))
A7: 6 | B7: dev_dotnet_junior | C7: SQL SELECT, JOIN | D7: Có hai bảng Orders và OrderDetails. Bảng Orders chứa thông tin đơn hàng, trong khi OrderDetails lưu chi tiết từng sản phẩm trong mỗi đơn hàng. Bạn cần lấy ra danh sách các đơn hàng cùng với tổng số lượng của từng sản phẩm. Cách viết truy vấn SQL đúng là gì? A. SELECT o.OrderId, SUM(od.Quantity) FROM Orders o JOIN OrderDetails od ON o.OrderId = od.OrderId GROUP BY o.OrderId ✓ B. SELECT o.OrderId, od.ProductId, SUM(od.Quantity) FROM Orders o JOIN OrderDetails od ON o.OrderId = od.OrderId GROUP BY o.OrderId, od.ProductId C. SELECT o.OrderId, SUM(od.Quantity) FROM Orders o JOIN OrderDetails od ON o.OrderId = od.OrderId GROUP BY o.OrderId, od.ProductId D. SELECT o.OrderId, od.ProductId, SUM(od.Quantity) FROM Orders o JOIN OrderDetails od ON o.OrderId = od.OrderId GROUP BY o.OrderId | J7: =IF(COUNT(E7:I7)=5,AVERAGE(E7:I7),"") | K7: =IF(J7="","",IF(J7>=4,"Đạt","Không"))
A8: 7 | B8: dev_dotnet_junior | C8: SQL SELECT, JOIN | D8: Bảng Employees và Departments có mối quan hệ một-đa. Bạn cần lấy ra danh sách các bộ phận cùng với số lượng nhân viên trong mỗi bộ phận. Cách viết truy vấn SQL đúng là gì? A. SELECT d.DepartmentName, COUNT(e.EmployeeId) FROM Employees e JOIN Departments d ON e.DepartmentId = d.DepartmentId GROUP BY d.DepartmentName ✓ B. SELECT d.DepartmentName, COUNT(e.EmployeeId) FROM Employees e JOIN Departments d ON e.DepartmentId = d.DepartmentId GROUP BY e.EmployeeId C. SELECT d.DepartmentName, COUNT(*) FROM Employees e JOIN Departments d ON e.DepartmentId = d.DepartmentId GROUP BY d.DepartmentName, e.EmployeeId D. SELECT d.DepartmentName, COUNT(e.EmployeeId) FROM Employees e JOIN Departments d ON e.DepartmentId = d.DepartmentId GROUP BY e.DepartmentId | J8: =IF(COUNT(E8:I8)=5,AVERAGE(E8:I8),"") | K8: =IF(J8="","",IF(J8>=4,"Đạt","Không"))
A9: 8 | B9: dev_dotnet_junior | C9: SQL SELECT, JOIN | D9: Bảng Products và Suppliers có mối quan hệ nhiều-nhiều. Bạn cần lấy ra danh sách các sản phẩm cùng với tên nhà cung cấp của chúng. Cách viết truy vấn SQL đúng là gì? A. SELECT p.ProductName, s.SupplierName FROM Products p JOIN Suppliers s ON p.SupplierId = s.SupplierId ✓ B. SELECT p.ProductName, s.SupplierName FROM Products p JOIN Suppliers s ON p.SupplierId = s.SupplierId WHERE p.SupplierId IS NOT NULL C. SELECT p.ProductName, s.SupplierName FROM Products p LEFT JOIN Suppliers s ON p.SupplierId = s.SupplierId D. SELECT p.ProductName, s.SupplierName FROM Products p RIGHT JOIN Suppliers s ON p.SupplierId = s.SupplierId | J9: =IF(COUNT(E9:I9)=5,AVERAGE(E9:I9),"") | K9: =IF(J9="","",IF(J9>=4,"Đạt","Không"))
A10: 9 | B10: dev_dotnet_junior | C10: Entity Framework Core | D10: Khi sử dụng Entity Framework Core để thực hiện truy vấn, bạn nhận thấy rằng việc lặp qua một danh sách lớn của đối tượng gây ra hiệu suất kém. Cách tiếp cận tốt nhất để cải thiện hiệu suất là gì? A. Sử dụng Include() để tải các bảng liên kết B. Tăng kích thước bộ đệm trong DbContext C. Thay đổi phương thức Linq thành SQL D. Thêm chỉ mục cho các cột được sử dụng trong điều kiện WHERE ✓ | J10: =IF(COUNT(E10:I10)=5,AVERAGE(E10:I10),"") | K10: =IF(J10="","",IF(J10>=4,"Đạt","Không"))
A11: 10 | B11: dev_dotnet_junior | C11: Entity Framework Core | D11: Bạn cần tạo một quan hệ 1:N giữa bảng Orders và OrderDetails. Cách thực hiện đúng là gì? A. Tạo một thuộc tính virtual OrderDetails[] trong class Order B. Thêm một thuộc tính virtual ICollection<Order> trong class OrderDetails C. Thêm một thuộc tính virtual Order trong class OrderDetails D. Sử dụng Fluent API để cấu hình quan hệ 1:N ✓ | J11: =IF(COUNT(E11:I11)=5,AVERAGE(E11:I11),"") | K11: =IF(J11="","",IF(J11>=4,"Đạt","Không"))
A12: 11 | B12: dev_dotnet_senior | C12: Thiết kế kiến trúc microservices | D12: Một ứng dụng microservices của bạn đang gặp vấn đề về độ trễ khi gửi thông báo qua dịch vụ tin nhắn SMS. Dịch vụ này thường mất khoảng 1-2 giây để phản hồi, nhưng đôi khi có thể lên đến 30 giây. Cách tiếp cận tốt nhất để giải quyết vấn đề này là gì? A. Tăng thời gian chờ đợi trong hàm gửi tin nhắn SMS B. Sử dụng retry mechanism với độ trễ tăng dần C. Thay đổi dịch vụ SMS thành một microservice độc lập và sử dụng queueing system ✓ D. Giảm số lượng yêu cầu gửi SMS đồng thời | J12: =IF(COUNT(E12:I12)=5,AVERAGE(E12:I12),"") | K12: =IF(J12="","",IF(J12>=4,"Đạt","Không"))
A13: 12 | B13: dev_dotnet_senior | C13: Thiết kế kiến trúc microservices | D13: Bạn nhận thấy rằng một microservice thường xuyên gặp lỗi khi xử lý các yêu cầu lớn từ dịch vụ API gateway. Điều này dẫn đến việc tăng độ trễ và giảm hiệu suất của hệ thống. Cách tiếp cận tốt nhất để giải quyết vấn đề này là gì? A. Tăng số lượng instance của microservice ✓ B. Giảm kích thước của các yêu cầu lớn từ API gateway C. Sử dụng load balancer để phân tán tải lên nhiều instance D. Thay đổi microservice thành một batch processing task | J13: =IF(COUNT(E13:I13)=5,AVERAGE(E13:I13),"") | K13: =IF(J13="","",IF(J13>=4,"Đạt","Không"))
... A120: 119 | B120: edge_jd_thieu_kythuat | C120: Quản lý lịch hẹn và lịch trình | D120: Chuyên viên văn phòng nhận được yêu cầu từ một bộ phận khác về việc thay đổi lịch họp. Tuy nhiên, trong hệ thống hiện tại không có chức năng cập nhật lịch hẹn trực tiếp từ bên ngoài. Cách xử lý hợp lý nhất là gì? A. Tạo một bản ghi mới cho cuộc họp mới B. Gửi email thông báo cho bộ phận khác về việc không thể thay đổi C. Yêu cầu bộ phận liên hệ trực tiếp với chuyên viên văn phòng để cập nhật D. Tạo một quy trình thủ công để cập nhật lịch hẹn ✓ | J120: =IF(COUNT(E120:I120)=5,AVERAGE(E120:I120),"") | K120: =IF(J120="","",IF(J120>=4,"Đạt","Không"))

Sheet v5_self_critique
A1: STT | B1: JD_id | C1: Skill | D1: Câu hỏi (đầy đủ) | E1: Correctness | F1: Relevance | G1: Distractor | H1: Tình huống | I1: Rõ ràng | J1: Điểm TB | K1: Đạt | L1: Ghi chú
A2: 1 | B2: dev_dotnet_junior | C2: C# OOP | D2: Bạn đang phát triển một ứng dụng quản lý thư viện. Bạn cần tạo một lớp `Sach` (Sách) để lưu thông tin sách, trong đó có các thuộc tính như `MaSach`, `TenSach`, `TacGia`. Để đảm bảo `MaSach` luôn duy nhất, bạn nên sử dụng phương thức nào sau đây? A. Tạo một phương thức `SetMaSach()` để gán giá trị cho `MaSach` B. Thêm thuộc tính `MaSach` làm thuộc tính chỉ đọc (`readonly`) và khởi tạo trong constructor ✓ C. Thêm phương thức `GetMaSach()` để trả về giá trị của `MaSach` D. Tạo một phương thức `CheckMaSachUniqueness()` để kiểm tra sự duy nhất của `MaSach` | J2: =IF(COUNT(E2:I2)=5,AVERAGE(E2:I2),"") | K2: =IF(J2="","",IF(J2>=4,"Đạt","Không"))
A3: 2 | B3: dev_dotnet_junior | C3: LINQ | D3: Công ty bạn cần lấy danh sách các sản phẩm có giá bán trên 100.000 đồng từ bảng Products để hiển thị trên trang quản trị. Bạn muốn tối ưu hóa truy vấn để tránh việc lặp qua toàn bộ bảng. Cách làm nào sau đây là hiệu quả nhất? A. Sử dụng LINQ với câu lệnh `var result = from p in Products where p.Price > 100000 select p;` B. Sử dụng phương thức `Where` và `Select` của LINQ: `var result = Products.Where(p => p.Price > 100000).ToList();` C. Lặp qua toàn bộ bảng Products bằng vòng lặp for và kiểm tra điều kiện giá bán. D. Tạo một index trên cột Price trước khi thực hiện truy vấn. ✓ | J3: =IF(COUNT(E3:I3)=5,AVERAGE(E3:I3),"") | K3: =IF(J3="","",IF(J3>=4,"Đạt","Không"))
A4: 3 | B4: dev_dotnet_junior | C4: HTTP/REST | D4: Một ứng dụng RESTful API của bạn nhận được nhiều yêu cầu GET từ một client không tin cậy, dẫn đến việc sử dụng quá nhiều tài nguyên. Cách tốt nhất để giải quyết vấn đề này là gì? A. Tăng số lượng worker thread trong server B. Thêm rate limiting vào endpoint ✓ C. Đổi phương thức HTTP từ GET thành POST D. Thay đổi API thành giao diện SOAP | J4: =IF(COUNT(E4:I4)=5,AVERAGE(E4:I4),"") | K4: =IF(J4="","",IF(J4>=4,"Đạt","Không"))
A5: 4 | B5: dev_dotnet_junior | C5: HTTP/REST | D5: Bạn nhận được yêu cầu từ client cần lấy danh sách sản phẩm theo loại, nhưng số lượng sản phẩm lớn và thường xuyên thay đổi. Để tối ưu hóa hiệu suất truy vấn, bạn nên làm gì? A. Tạo một index trên cột Loại B. Thực hiện truy vấn SQL phức tạp hơn C. Sử dụng phương thức HTTP POST thay vì GET D. Lưu danh sách sản phẩm trong bộ nhớ cache ✓ | J5: =IF(COUNT(E5:I5)=5,AVERAGE(E5:I5),"") | K5: =IF(J5="","",IF(J5>=4,"Đạt","Không"))
A6: 5 | B6: dev_dotnet_junior | C6: SQL SELECT, JOIN | D6: Có hai bảng Orders và OrderDetails. Bảng Orders chứa thông tin đơn hàng, trong khi OrderDetails lưu chi tiết từng sản phẩm trong mỗi đơn hàng. Bạn cần lấy ra danh sách các đơn hàng cùng với tổng số lượng của từng sản phẩm. Cách thực hiện đúng là gì? A. SELECT o.OrderId, SUM(od.Quantity) FROM Orders o JOIN OrderDetails od ON o.OrderId = od.OrderId GROUP BY o.OrderId ✓ B. SELECT o.OrderId, SUM(od.Quantity) FROM Orders o INNER JOIN OrderDetails od ON o.OrderId = od.OrderId ORDER BY o.OrderId C. - Lỗi hiểu sai: Người ta thường nhầm lẫn giữa `GROUP BY` và `ORDER BY`. D. SELECT o.OrderId, SUM(od.Quantity) FROM Orders o LEFT JOIN OrderDetails od ON o.OrderId = od.OrderId GROUP BY o.OrderId | J6: =IF(COUNT(E6:I6)=5,AVERAGE(E6:I6),"") | K6: =IF(J6="","",IF(J6>=4,"Đạt","Không"))
A7: 6 | B7: dev_dotnet_junior | C7: SQL SELECT, JOIN | D7: Bạn cần lấy ra danh sách các sản phẩm mà khách hàng đã mua trong năm nay. Bảng Customers chứa thông tin về khách hàng, Orders chứa thông tin đơn hàng và OrderDetails lưu chi tiết từng sản phẩm. Cách thực hiện đúng là gì? A. SELECT p.ProductName FROM Products p JOIN (SELECT ProductId FROM OrderDetails WHERE OrderId IN (SELECT OrderId FROM Orders WHERE YEAR(OrderDate) = YEAR(CURRENT_DATE()))) od ON p.ProductId = od.ProductId B. - Lỗi hiểu sai: Người ta thường nhầm lẫn giữa `JOIN` và `IN`. ✓ C. SELECT p.ProductName FROM Products p INNER JOIN OrderDetails od ON p.ProductId = od.ProductId WHERE od.OrderId IN (SELECT OrderId FROM Orders WHERE YEAR(OrderDate) = YEAR(CURRENT_DATE())) D. - Đáp án đúng, nhưng để đáp án này ở vị trí thứ hai để tăng độ khó. | J7: =IF(COUNT(E7:I7)=5,AVERAGE(E7:I7),"") | K7: =IF(J7="","",IF(J7>=4,"Đạt","Không"))
A8: 7 | B8: dev_dotnet_junior | C8: SQL SELECT, JOIN | D8: Bảng Employees chứa thông tin nhân viên, trong khi Orders lưu thông tin đơn hàng. Bạn cần lấy ra danh sách các nhân viên cùng với tổng số lượng đơn hàng họ đã thực hiện. Cách thực hiện đúng là gì? A. SELECT e.EmployeeName, COUNT(o.OrderId) FROM Employees e JOIN Orders o ON e.EmployeeId = o.EmployeeId GROUP BY e.EmployeeId ✓ B. SELECT e.EmployeeName, COUNT(o.OrderId) FROM Employees e INNER JOIN Orders o ON e.EmployeeId = o.EmployeeId ORDER BY e.EmployeeId C. - Lỗi hiểu sai: Người ta thường nhầm lẫn giữa `GROUP BY` và `ORDER BY`. D. SELECT e.EmployeeName, COUNT(o.OrderId) FROM Employees e LEFT JOIN Orders o ON e.EmployeeId = o.EmployeeId GROUP BY e.EmployeeId | J8: =IF(COUNT(E8:I8)=5,AVERAGE(E8:I8),"") | K8: =IF(J8="","",IF(J8>=4,"Đạt","Không"))
A9: 8 | B9: dev_dotnet_junior | C9: Entity Framework Core | D9: Khi sử dụng Entity Framework Core để quản lý cơ sở dữ liệu của một cửa hàng bán lẻ, bạn phát hiện rằng tốc độ truy vấn thông tin về các sản phẩm chậm dù đã tối ưu hóa chỉ mục. Cách tiếp cận nào sau đây sẽ giúp cải thiện hiệu suất? A. Tăng số lượng CPU trên máy chủ B. Thay đổi phương thức truy vấn từ Include() sang ThenInclude() C. Đổi Entity Framework Core thành ADO.NET D. Thêm chỉ mục compound lên các cột thường được lọc cùng nhau ✓ | J9: =IF(COUNT(E9:I9)=5,AVERAGE(E9:I9),"") | K9: =IF(J9="","",IF(J9>=4,"Đạt","Không"))
A10: 9 | B10: dev_dotnet_junior | C10: Entity Framework Core | D10: Bạn cần thiết kế một hệ thống quản lý đơn hàng (Order) và chi tiết đơn hàng (OrderDetail). Trong trường hợp này, thuộc tính nào trong lớp Order sẽ được sử dụng để liên kết với nhiều OrderDetail? A. public virtual ICollection<OrderDetail> OrderDetails { get; set; } ✓ B. public virtual List<OrderDetail> Details { get; set; } C. public virtual IEnumerable<OrderDetail> Orders { get; set; } D. public virtual OrderDetail Detail { get; set; } | J10: =IF(COUNT(E10:I10)=5,AVERAGE(E10:I10),"") | K10: =IF(J10="","",IF(J10>=4,"Đạt","Không"))
A11: 10 | B11: dev_dotnet_junior | C11: API RESTful | D11: Bạn đang phát triển một API RESTful cho ứng dụng quản lý dự án. Trong quá trình thử nghiệm, bạn nhận thấy rằng khi nhiều người dùng cùng lúc truy cập vào API để lấy danh sách các dự án của họ, thời gian phản hồi trở nên chậm chạp. Bạn đã kiểm tra và xác định rằng vấn đề nằm ở việc xử lý dữ liệu trong hàm xử lý yêu cầu. Để cải thiện hiệu suất, bạn nên làm gì? A. Tăng số lượng CPU trên máy chủ B. Sử dụng LINQ để tối ưu hóa truy vấn cơ sở dữ liệu C. Chuyển đổi từ phương thức GET sang POST cho tất cả các API D. Tách xử lý dữ liệu ra khỏi hàm xử lý yêu cầu và sử dụng Task.Run để thực hiện đồng thời ✓ | J11: =IF(COUNT(E11:I11)=5,AVERAGE(E11:I11),"") | K11: =IF(J11="","",IF(J11>=4,"Đạt","Không"))
A12: 11 | B12: dev_dotnet_senior | C12: Thiết kế kiến trúc microservices | D12: Một ứng dụng của bạn sử dụng microservices, trong đó có một microservice xử lý gửi thông báo qua dịch vụ tin nhắn SMS. Tuy nhiên, bạn nhận thấy rằng đôi khi quá trình này bị chậm trễ đáng kể, thậm chí lên đến 30 giây. Dịch vụ SMS thường phản hồi trong khoảng 1-2 giây. Để cải thiện tình hình, cách tiếp cận tốt nhất là gì? A. Tăng thời gian chờ đợi trong hàm gửi tin nhắn SMS để đảm bảo không bị lỗi timeout. B. Sử dụng retry mechanism với độ trễ tăng dần để tự động thử lại khi gặp vấn đề. C. Thay đổi dịch vụ SMS thành một microservice độc lập và sử dụng queueing system để tách biệt quá trình xử lý yêu cầu. ✓ D. Giảm số lượng yêu cầu gửi SMS đồng thời để giảm tải cho dịch vụ SMS. | J12: =IF(COUNT(E12:I12)=5,AVERAGE(E12:I12),"") | K12: =IF(J12="","",IF(J12>=4,"Đạt","Không"))
A13: 12 | B13: dev_dotnet_senior | C13: Thiết kế kiến trúc microservices | D13: Bạn phát hiện ra rằng một microservice thường xuyên gặp lỗi khi xử lý các yêu cầu lớn từ API gateway, dẫn đến tăng độ trễ và giảm hiệu suất của hệ thống. Để giải quyết vấn đề này, cách tiếp cận tốt nhất là gì? A. Tăng số lượng instance của microservice để nâng cao khả năng chịu tải. B. Giảm kích thước của các yêu cầu lớn từ API gateway để giảm áp lực lên microservice. C. Sử dụng load balancer để phân tán tải lên nhiều instance của microservice. D. Thay đổi microservice thành một batch processing task để xử lý yêu cầu lớn một cách hiệu quả. ✓ | J13: =IF(COUNT(E13:I13)=5,AVERAGE(E13:I13),"") | K13: =IF(J13="","",IF(J13>=4,"Đạt","Không"))
... A112: 111 | B112: edge_jd_thieu_kythuat | C112: Quản lý lịch hẹn và lịch trình | D112: Chuyên viên văn phòng nhận được yêu cầu từ một bộ phận khác để thay đổi lịch họp của sếp. Tuy nhiên, sếp đang bận với một dự án quan trọng và không thể thay đổi lịch trình. Cách xử lý phù hợp nhất là gì? A. Thay đổi lịch họp ngay lập tức theo yêu cầu B. Gửi email cho bộ phận khác giải thích tình hình C. Yêu cầu sếp xác nhận lại lịch họp trước khi thực hiện ✓ D. Từ chối thay đổi lịch họp và không thông báo cho bất kỳ ai | J112: =IF(COUNT(E112:I112)=5,AVERAGE(E112:I112),"") | K112: =IF(J112="","",IF(J112>=4,"Đạt","Không"))
